[
  {
    "PersonId": 1,
    "FirstName": "Owen",
    "LastName": "Marsh",
    "PhoneNumber": "0725-11 71 34"
  },
  {
    "PersonId": 2,
    "FirstName": "Cheyenne",
    "LastName": "Willis",
    "PhoneNumber": "0730-24 18 39"
  },
  {
    "PersonId": 3,
    "FirstName": "Justin",
    "LastName": "Ortiz",
    "PhoneNumber": "0715-83 45 79"
  },
  {
    "PersonId": 4,
    "FirstName": "Declan",
    "LastName": "Burns",
    "PhoneNumber": "0715-07 88 73"
  },
  {
    "PersonId": 5,
    "FirstName": "Otto",
    "LastName": "Clements",
    "PhoneNumber": "0795-86 28 17"
  },
  {
    "PersonId": 6,
    "FirstName": "Yardley",
    "LastName": "Webb",
    "PhoneNumber": "0795-65 65 88"
  },
  {
    "PersonId": 7,
    "FirstName": "Octavius",
    "LastName": "Flores",
    "PhoneNumber": "0738-18 40 65"
  },
  {
    "PersonId": 8,
    "FirstName": "Kermit",
    "LastName": "Maxwell",
    "PhoneNumber": "0767-83 35 84"
  },
  {
    "PersonId": 9,
    "FirstName": "Garrison",
    "LastName": "Bryant",
    "PhoneNumber": "0739-76 66 19"
  },
  {
    "PersonId": 10,
    "FirstName": "Keane",
    "LastName": "Rasmussen",
    "PhoneNumber": "0724-13 64 81"
  },
  {
    "PersonId": 11,
    "FirstName": "Scarlet",
    "LastName": "Keller",
    "PhoneNumber": "0712-37 27 00"
  },
  {
    "PersonId": 12,
    "FirstName": "Trevor",
    "LastName": "West",
    "PhoneNumber": "0751-22 72 78"
  },
  {
    "PersonId": 13,
    "FirstName": "Curran",
    "LastName": "Pruitt",
    "PhoneNumber": "0759-76 21 08"
  },
  {
    "PersonId": 14,
    "FirstName": "Dorian",
    "LastName": "Hines",
    "PhoneNumber": "0791-59 25 44"
  },
  {
    "PersonId": 15,
    "FirstName": "Kieran",
    "LastName": "Chapman",
    "PhoneNumber": "0710-67 68 13"
  }
]